Workbook

Sheet Dashboard
B2: Assurance Bank
B4: Income and Profit Analysis
B7: =COUNTA(Income_to_Cost_Ratio!C24:C31) -> 8 | H7: =COUNTA(Region_Profitability!A2:A6) -> 5 | L7: =COUNTA(Branch_Profitability!B2:B30) -> 29 | P7: =COUNTA(Segment_Income!B2:B5) -> 4 | T7: =COUNTA(Product_Profitability!D2:J2) -> 7 | X7: -891325.26 | AB7: =COUNTA(Pivot_Tables!G4:G28) -> 25
B9: Branches with Income to Cost <1 | H9: Regions | L9: Branches | P9: Segments | T9: Products | X9: Loss Value | AB9: No. of Branches
X10: Severe Loss on Savings Product

Sheet Pivot_Tables
A2: Top and Worst Revenue Making Branches | D2: Top and Worst Product Profitability | G2: Severe Loss Making | J2: Income to Cost Ratio
A3: Row Labels | B3: Sum of revenue | D3: Row Labels | E3: Sum of value | G3: Row Labels | H3: Sum of savings_profit | J3: Row Labels | K3: Sum of income_to_cost_ratio
A4: Red Deer Branch | B4: 5372857.3 | D4: Bonnyvile Branch | E4: -856479.79 | G4: Lloydminster Branch | H4: -7191.36 | J4: Red Deer Branch | K4: 7.08
A5: St. Albert Branch | B5: 3991337.8 | D5: credit card | E5: -243590.34 | G5: Aspen Branch | H5: -10454.61 | J5: Grand Prairie Branch | K5: 4.31
A6: Grand Prairie Branch | B6: 3778639.1 | D6: mortgage | E6: -612889.45 | G6: Bighorn Branch | H6: -12065.32 | J6: Edmonton North Branch | K6: 3.69
A7: Leduc Branch | B7: 1169121.5 | D7: Borealis Branch | E7: -326353.91 | G7: Calgary South Branch | H7: -13020.05 | J7: Calgary South Branch | K7: 3.02
A8: Rocky Mountain Branch | B8: 1127087.1 | D8: mortgage | E8: -326353.91 | G8: Mosaic Branch | H8: -14112.87 | J8: Edmonton South Branch | K8: 2.65
A9: Bonnyvile Branch | B9: 500247.08 | D9: mortgage | E9: 3252840.5 | G9: Chinook Branch | H9: -18451.56 | J9: Aspen Branch | K9: 2.56
A10: Grand Total | B10: 15939290 | D10: Red Deer Branch | E10: 1434496.3 | G10: Edmonton South Branch | H10: -18508.29 | J10: Sherwood Park Branch | K10: 2.54
D11: Sherwood Park Branch | E11: 708881.13 | G11: Mcleod River Branch | H11: -19385 | J11: Bighorn Branch | K11: 2.27
D12: St. Albert Branch | E12: 1109463.1 | G12: Bow Valley Branch | H12: -21213.06 | J12: St. Albert Branch | K12: 2.13
A13: Top and Worst Profit Making Branches | D13: Grand Total | E13: 2070006.8 | G13: Camrose Branch | H13: -23047.64 | J13: Lakeland Branch | K13: 2.03
A14: Row Labels | B14: Sum of profit | G14: Palliser Branch | H14: -23458.05 | J14: Calgary West Branch | K14: 1.7
A15: Red Deer Branch | B15: 4614393.3 | G15: Calgary West Branch | H15: -24316.51 | J15: Drayton Valley Branch | K15: 1.53
A16: Grand Prairie Branch | B16: 2901585.3 | D16: Region Profitability | G16: Rocky Mountain Branch | H16: -24346.67 | J16: Wetaskiwin Branch | K16: 1.4
A17: Edmonton North Branch | B17: 2553392.9 | D17: Row Labels | E17: Sum of region_profit | G17: Calgary Foothills Branch | H17: -27606.54 | J17: Mosaic Branch | K17: 1.28
A18: Leduc Branch | B18: -994622.48 | D18: Central | E18: 7172463.7 | G18: Leduc Branch | H18: -27880.64 | J18: Camrose Branch | K18: 1.26
A19: Bonnyvile Branch | B19: -1143633.6 | D19: Edmonton | E19: 7140142.8 | G19: Cold Lake Branch | H19: -30158.81 | J19: Palliser Branch | K19: 1.26
A20: Borealis Branch | B20: -1356792.6 | D20: North | E20: 5563111 | G20: Wood Buffalo Branch | H20: -33102.84 | J20: Chinook Branch | K20: 1.24
A21: Grand Total | B21: 6574322.8 | D21: Calgary | E21: 2425064.3 | G21: Wetaskiwin Branch | H21: -35397.71 | J21: Northwest Branch | K21: 1.2
D22: South | E22: 1219318.2 | G22: Northwest Branch | H22: -37443.45 | J22: Wood Buffalo Branch | K22: 1.09
D23: Grand Total | E23: 23520100 | G23: Edmonton North Branch | H23: -56929.91 | J23: Cold Lake Branch | K23: 1.07
A24: Segment Income | G24: Lakeland Branch | H24: -68941.67 | J24: Lloydminster Branch | K24: 1.04
A25: Row Labels | B25: Sum of segment_income | G25: Calgary Rural Branch | H25: -77803.92 | J25: Calgary Rural Branch | K25: 0.99
A26: SME | B26: 32998423 | G26: Drayton Valley Branch | H26: -84676.19 | J26: Bow Valley Branch | K26: 0.88
A27: retail | B27: 19952535 | G27: Borealis Branch | H27: -88943.38 | J27: Mcleod River Branch | K27: 0.85
A28: corporate | B28: 14580699 | G28: Bonnyvile Branch | H28: -92869.21 | J28: Calgary Foothills Branch | K28: 0.75
A29: prestige | B29: 9208862.3 | G29: Grand Total | H29: -891325.26 | J29: Rocky Mountain Branch | K29: 0.67
A30: Grand Total | B30: 76740519 | J30: Leduc Branch | K30: 0.54
J31: Borealis Branch | K31: 0.52
J32: Bonnyvile Branch | K32: 0.3
J33: Grand Total | K33: 51.85

Sheet Branch_Profitability
A1: branch_code | B1: branch_name | C1: branch_manager_name | D1: reporting_period | E1: total_income | F1: operating_expense | G1: net_profit_or_loss
A2: 12 | B2: Red Deer Branch | C2: Elina Sellers | D2: FY2025 | E2: 5372857.3 | F2: 758463.99 | G2: 4614393.3
A3: 23 | B3: Grand Prairie Branch | C3: Zakai Doyle | D3: FY2025 | E3: 3778639.1 | F3: 877053.79 | G3: 2901585.3 | I3: branch_name | J3: branch_manager | K3: revenue
A4: 13 | B4: Edmonton North Branch | C4: Amanda Sloan | D4: FY2025 | E4: 3501543.1 | F4: 948150.28 | G4: 2553392.9 | I4: Red Deer Branch | J4: Elina Sellers | K4: =LARGE(Table1[total_income], 1) -> 5372857.3
A5: 16 | B5: Sherwood Park Branch | C5: Blair Keith | D5: FY2025 | E5: 3610413.7 | F5: 1423018.8 | G5: 2187394.9 | I5: St. Albert Branch | J5: Kira Parra | K5: =LARGE(Table1[total_income], 2) -> 3991337.8
A6: 17 | B6: St. Albert Branch | C6: Kira Parra | D6: FY2025 | E6: 3991337.8 | F6: 1869712.6 | G6: 2121625.2 | I6: Grand Prairie Branch | J6: Zakai Doyle | K6: =LARGE(Table1[total_income], 3) -> 3778639.1
A7: 4 | B7: Calgary South Branch | C7: Kimber Strong | D7: FY2025 | E7: 2946087.8 | F7: 975066.77 | G7: 1971021 | I7: Leduc Branch | J7: Ivanna Berry | K7: =LARGE(Table1[total_income], 27) -> 1169121.5
A8: 24 | B8: Bighorn Branch | C8: Caspian Palmer | D8: FY2025 | E8: 3097706.4 | F8: 1366428.3 | G8: 1731278 | I8: Rocky Mountain Branch | J8: Kora Lu | K8: =LARGE(Table1[total_income], 28) -> 1127087.1
A9: 25 | B9: Aspen Branch | C9: Declan Bradshaw | D9: FY2025 | E9: 2745053.5 | F9: 1070809 | G9: 1674244.6 | I9: Bonnyvile Branch | J9: Amoura Potter | K9: =LARGE(Table1[total_income], 29) -> 500247.08
A10: 19 | B10: Lakeland Branch | C10: Marilyn Burch | D10: FY2025 | E10: 2586614.9 | F10: 1273372.1 | G10: 1313242.8
A11: 14 | B11: Edmonton South Branch | C11: Lyric Jenkins | D11: FY2025 | E11: 2044639.4 | F11: 772287.13 | G11: 1272352.3
A12: 3 | B12: Calgary West Branch | C12: Amari Correa | D12: FY2025 | E12: 3029376.5 | F12: 1786094.3 | G12: 1243282.1
A13: 10 | B13: Drayton Valley Branch | C13: Skyla Boyd | D13: FY2025 | E13: 2901061 | F13: 1902285.5 | G13: 998775.52 | I13: branch_name | J13: branch_manager | K13: profit
A14: 8 | B14: Wetaskiwin Branch | C14: Liberty Jenkins | D14: FY2025 | E14: 3463287.2 | F14: 2473224.5 | G14: 990062.72 | I14: Red Deer Branch | J14: Elina Sellers | K14: =LARGE(Table1[net_profit_or_loss], 1) -> 4614393.3
A15: 29 | B15: Palliser Branch | C15: Gerald Wong | D15: FY2025 | E15: 3407998.1 | F15: 2704359.4 | G15: 703638.78 | I15: Grand Prairie Branch | J15: Zakai Doyle | K15: =LARGE(Table1[net_profit_or_loss], 2) -> 2901585.3
A16: 5 | B16: Mosaic Branch | C16: Fallon Edwards | D16: FY2025 | E16: 3000896.6 | F16: 2340463 | G16: 660433.64 | I16: Edmonton North Branch | J16: Amanda Sloan | K16: =LARGE(Table1[net_profit_or_loss], 3) -> 2553392.9
A17: 18 | B17: Northwest Branch | C17: Anika Hicks | D17: FY2025 | E17: 3340331.8 | F17: 2787402.9 | G17: 552928.91 | I17: Leduc Branch | J17: Ivanna Berry | K17: =LARGE(Table1[net_profit_or_loss], 27) -> -994622.48
A18: 28 | B18: Chinook Branch | C18: Dean Rowe | D18: FY2025 | E18: 2672508.1 | F18: 2156828.6 | G18: 515679.46 | I18: Bonnyvile Branch | J18: Amoura Potter | K18: =LARGE(Table1[net_profit_or_loss], 28) -> -1143633.6
A19: 9 | B19: Camrose Branch | C19: Mya Lane | D19: FY2025 | E19: 2318465.4 | F19: 1835729.9 | G19: 482735.52 | I19: Borealis Branch | J19: Duncan Oâ€™Connor | K19: =LARGE(Table1[net_profit_or_loss], 29) -> -1356792.6
A20: 21 | B20: Cold Lake Branch | C20: Blake Rich | D20: FY2025 | E20: 2609944.6 | F20: 2437767.6 | G20: 172176.97
A21: 22 | B21: Wood Buffalo Branch | C21: Avery Mullen | D21: FY2025 | E21: 1339939.1 | F21: 1226235.8 | G21: 113703.3
A22: 7 | B22: Lloydminster Branch | C22: Zariyah Roach | D22: FY2025 | E22: 2077434.1 | F22: 1990937.6 | G22: 86496.59
A23: 2 | B23: Calgary Rural Branch | C23: Stella Duncan | D23: FY2025 | E23: 2706373.7 | F23: 2740589.3 | G23: -34215.64
A24: 1 | B24: Bow Valley Branch | C24: Emery Elliott | D24: FY2025 | E24: 1912874.2 | F24: 2166382.2 | G24: -253507.98
A25: 27 | B25: Mcleod River Branch | C25: Jedidiah Lu | D25: FY2025 | E25: 2163054.3 | F25: 2558676.9 | G25: -395622.57
A26: 11 | B26: Rocky Mountain Branch | C26: Kora Lu | D26: FY2025 | E26: 1127087.1 | F26: 1683344.3 | G26: -556257.26
A27: 6 | B27: Calgary Foothills Branch | C27: Jemma Rosario | D27: FY2025 | E27: 1844114 | F27: 2449805.6 | G27: -605691.61
A28: 15 | B28: Leduc Branch | C28: Ivanna Berry | D28: FY2025 | E28: 1169121.5 | F28: 2163744 | G28: -994622.48
A29: 20 | B29: Bonnyvile Branch | C29: Amoura Potter | D29: FY2025 | E29: 500247.08 | F29: 1643880.7 | G29: -1143633.6
A30: 26 | B30: Borealis Branch | C30: Duncan Oâ€™Connor | D30: FY2025 | E30: 1481512 | F30: 2838304.6 | G30: -1356792.6

Sheet Product_Profitability
A2: branch_code | B2: branch_name | C2: reporting_period | D2: checking_profit | E2: savings_profit | F2: personal_income_profit | G2: mortgage_profit | H2: credit_card_profit | I2: line_of_credit_profit | J2: GIC_profit
A3: 17 | B3: St. Albert Branch | C3: FY2025 | D3: 301402.92 | E3: 28723.32 | F3: 416667.03 | G3: 1267534.4 | H3: 365563.59 | I3: 353625.37 | J3: 76469.74
A4: 16 | B4: Sherwood Park Branch | C4: FY2025 | D4: 265217.58 | E4: 21344.44 | F4: 367626.11 | G4: 1109463.1 | H4: 316762.28 | I4: 317557.38 | J4: 67780.36
A5: 23 | B5: Grand Prairie Branch | C5: FY2025 | D5: 263666.69 | E5: 13646.12 | F5: 367369.75 | G5: 1091615.1 | H5: 305443.09 | I5: 328007.38 | J5: 68330.7
A6: 12 | B6: Red Deer Branch | C6: FY2025 | D6: 351373.55 | E6: 4694.17 | F6: 492945.52 | G6: 1434496.3 | H6: 390182.54 | I6: 459039.96 | J6: 92746.83 | M6: product | N6: branch | O6: value
A7: 7 | B7: Lloydminster Branch | C7: FY2025 | D7: 121449.62 | E7: -7191.36 | F7: 172586.37 | G7: 482602.05 | H7: 123846.32 | I7: 172986.22 | J7: 33158.97 | M7: mortgage | N7: Red Deer Branch | O7: =LARGE(D3:J31,1) -> 1434496.3
A8: 25 | B8: Aspen Branch | C8: FY2025 | D8: 158956.05 | E8: -10454.61 | F8: 226145.6 | G8: 630077.03 | H8: 160789.91 | I8: 228102.25 | J8: 43529.53 | M8: mortgage | N8: St. Albert Branch | O8: =LARGE(D4:J32,2) -> 1109463.1
A9: 24 | B9: Bighorn Branch | C9: FY2025 | D9: 178948.7 | E9: -12065.32 | F9: 254662.94 | G9: 708881.13 | H9: 180643.5 | I9: 257272.38 | J9: 49041.42 | M9: mortgage | N9: Sherwood Park Branch | O9: =LARGE(D5:J33,3) -> 708881.13
A10: 4 | B10: Calgary South Branch | C10: FY2025 | D10: 167717.53 | E10: -13020.05 | F10: 239107.78 | G10: 661822.38 | H10: 167165.98 | I10: 243907.43 | J10: 46177.48 | M10: Bonnyvile Branch | N10: credit card | O10: =SMALL(D3:J31, 3) -> -243590.34
A11: 5 | B11: Mosaic Branch | C11: FY2025 | D11: 169476.79 | E11: -14112.87 | F11: 241854.96 | G11: 667330.16 | H11: 167724.16 | I11: 248019.78 | J11: 46781.38 | M11: Borealis Branch | N11: mortgage | O11: =SMALL(D4:J32, 2) -> -326353.91
A12: 28 | B12: Chinook Branch | C12: FY2025 | D12: 141518.03 | E12: -18451.56 | F12: 203622.61 | G12: 547239.65 | H12: 131720.9 | I12: 217937.41 | J12: 39897.17 | M12: Bonnyvile Branch | N12: mortgage | O12: =SMALL(D5:J33, 1) -> -612889.45
A13: 14 | B13: Edmonton South Branch | C13: FY2025 | D13: 101243.66 | E13: -18508.29 | F13: 147000.98 | G13: 383539.96 | H13: 87599.9 | I13: 164540.21 | J13: 29206.39
A14: 27 | B14: Mcleod River Branch | C14: FY2025 | D14: 107419.48 | E14: -19385 | F14: 155904.9 | G14: 407314.16 | H14: 93258.82 | I14: 174167.12 | J14: 30956.43
A15: 1 | B15: Bow Valley Branch | C15: FY2025 | D15: 88483.06 | E15: -21213.06 | F15: 129732.56 | G15: 327642.85 | H15: 70262.03 | I15: 151987.78 | J15: 26154.94
A16: 9 | B16: Camrose Branch | C16: FY2025 | D16: 111505.56 | E16: -23047.64 | F16: 162566.6 | G16: 418419.89 | H16: 93149.66 | I16: 185545.74 | J16: 32499.62
A17: 29 | B17: Palliser Branch | C17: FY2025 | D17: 180579 | E17: -23458.05 | F17: 259803.74 | G17: 698415.14 | H17: 168185.72 | I17: 277950.82 | J17: 50898.55
A18: 3 | B18: Calgary West Branch | C18: FY2025 | D18: 154973.68 | E18: -24316.51 | F18: 224010.86 | G18: 593105.81 | H18: 139106.83 | I18: 245338.74 | J18: 44204.45
A19: 11 | B19: Rocky Mountain Branch | C19: FY2025 | D19: 33178.91 | E19: -24346.67 | F19: 52744.51 | G19: 98269.31 | H19: 5856.1 | I19: 83629.07 | J19: 11856.48
A20: 6 | B20: Calgary Foothills Branch | C20: FY2025 | D20: 73852.83 | E20: -27606.54 | F20: 110757.17 | G20: 258617.29 | H20: 46268.35 | I20: 142946.42 | J20: 23067.97
A21: 15 | B21: Leduc Branch | C21: FY2025 | D21: 30214.77 | E21: -27880.64 | F21: 49459.67 | G21: 80926.53 | H21: -1803.39 | I21: 85435.01 | J21: 11510.88
A22: 21 | B22: Cold Lake Branch | C22: FY2025 | D22: 118782.35 | E22: -30158.81 | F22: 174577.37 | G22: 437315.06 | H22: 92219.67 | I22: 206765.88 | J22: 35321.41
A23: 22 | B23: Wood Buffalo Branch | C23: FY2025 | D23: 32791.56 | E23: -33102.84 | F23: 54388.84 | G23: 83561.43 | H23: -5512.79 | I23: 97343.4 | J23: 12848.11
A24: 8 | B24: Wetaskiwin Branch | C24: FY2025 | D24: 165014.05 | E24: -35397.71 | F24: 240900.43 | G24: 617272.99 | H24: 136236.97 | I24: 276680.56 | J24: 48256.56
... A31: 20 | B31: Bonnyvile Branch | C31: FY2025 | D31: -116574.92 | E31: -92869.21 | F31: -140716.18 | G31: -612889.45 | H31: -243590.34 | I31: -3913.6 | J31: -19356.56

Sheet Segment_Income
A1: segment_name | B1: segment_income
A2: retail | B2: 19952535
A3: SME | B3: 32998423
A4: corporate | B4: 14580699
A5: prestige | B5: 9208862.3

Sheet Region_Profitability
A1: branch_region | B1: region_profit
A2: Calgary | B2: 2425064.3
A3: Central | B3: 7172463.7
A4: Edmonton | B4: 7140142.8
A5: North | B5: 5563111
A6: South | B6: 1219318.2

Sheet Income_to_Cost_Ratio
B2: branch_code | C2: branch_name | D2: income_to_cost_ratio
B3: 12 | C3: Red Deer Branch | D3: 7.08
B4: 23 | C4: Grand Prairie Branch | D4: 4.31
B5: 13 | C5: Edmonton North Branch | D5: 3.69
B6: 4 | C6: Calgary South Branch | D6: 3.02
B7: 14 | C7: Edmonton South Branch | D7: 2.65
B8: 25 | C8: Aspen Branch | D8: 2.56
B9: 16 | C9: Sherwood Park Branch | D9: 2.54
B10: 24 | C10: Bighorn Branch | D10: 2.27
B11: 17 | C11: St. Albert Branch | D11: 2.13
B12: 19 | C12: Lakeland Branch | D12: 2.03
B13: 3 | C13: Calgary West Branch | D13: 1.7
B14: 10 | C14: Drayton Valley Branch | D14: 1.53
... B31: 20 | C31: Bonnyvile Branch | D31: 0.3
